drift/README.md
drift/__init__.py
drift/init_script.sh
drift/read.md
drift/requirements.txt
drift/run.py
drift/test.py
drift/__pycache__/__init__.cpython-39.pyc
drift/__pycache__/run.cpython-39.pyc
drift/__pycache__/test.cpython-39.pyc
drift/evidently/__init__.py
drift/evidently/__main__.py
drift/evidently/_config.py
drift/evidently/_version.py
drift/evidently/base_metric.py
drift/evidently/core.py
drift/evidently/metric_results.py
drift/evidently/pydantic_utils.py
drift/evidently/telemetry.py
drift/evidently/__pycache__/__init__.cpython-39.pyc
drift/evidently/__pycache__/__main__.cpython-39.pyc
drift/evidently/__pycache__/_config.cpython-39.pyc
drift/evidently/__pycache__/_version.cpython-39.pyc
drift/evidently/__pycache__/base_metric.cpython-39.pyc
drift/evidently/__pycache__/core.cpython-39.pyc
drift/evidently/__pycache__/metric_results.cpython-39.pyc
drift/evidently/__pycache__/pydantic_utils.cpython-39.pyc
drift/evidently/__pycache__/telemetry.cpython-39.pyc
drift/evidently/calculations/__init__.py
drift/evidently/calculations/classification_performance.py
drift/evidently/calculations/data_drift.py
drift/evidently/calculations/data_integration.py
drift/evidently/calculations/data_quality.py
drift/evidently/calculations/regression_performance.py
drift/evidently/calculations/utils.py
drift/evidently/calculations/__pycache__/__init__.cpython-39.pyc
drift/evidently/calculations/__pycache__/classification_performance.cpython-39.pyc
drift/evidently/calculations/__pycache__/data_drift.cpython-39.pyc
drift/evidently/calculations/__pycache__/data_integration.cpython-39.pyc
drift/evidently/calculations/__pycache__/data_quality.cpython-39.pyc
drift/evidently/calculations/__pycache__/regression_performance.cpython-39.pyc
drift/evidently/calculations/__pycache__/utils.cpython-39.pyc
drift/evidently/calculations/stattests/__init__.py
drift/evidently/calculations/stattests/anderson_darling_stattest.py
drift/evidently/calculations/stattests/chisquare_stattest.py
RefractMLMonitor-1.2.3.dist-info/METADATA
RefractMLMonitor-1.2.3.dist-info/WHEEL
RefractMLMonitor-1.2.3.dist-info/top_level.txt
RefractMLMonitor-1.2.3.dist-info/RECORD
